yrange/__init__.py
yrange/yrange.py
yrange-1.1.0.dist-info/LICENSE
yrange-1.1.0.dist-info/METADATA
yrange-1.1.0.dist-info/WHEEL
yrange-1.1.0.dist-info/top_level.txt
yrange-1.1.0.dist-info/RECORD
