Metadata-Version: 2.1
Name: yrange
Version: 1.1.0
Summary: Use generator for range function
Home-page: https://github.com/nimafanniasl/py_yrange
Author: Nima Fanniasl
Author-email: info@smartnima.com
License: UNKNOWN
Project-URL: Bug Tracker, https://github.com/nimafanniasl/py_yrange/issues
Platform: UNKNOWN
Classifier: Programming Language :: Python :: 3
Classifier: License :: OSI Approved :: GNU General Public License v3 (GPLv3)
Classifier: Operating System :: OS Independent
Requires-Python: >=3.6
License-File: LICENSE
